autowzry/__init__.py
autowzry/tiyanfu.py
autowzry/wzry.py
autowzry/wzyd.py
autowzry/assets/960.540.dict.yaml
autowzry/assets/tpl1686048521443.png
autowzry/assets/tpl1689665455905.png
autowzry/assets/tpl1689665490071.png
autowzry/assets/tpl1689665540773.png
autowzry/assets/tpl1689665577871.png
autowzry/assets/tpl1689666019941.png
autowzry/assets/tpl1689666034409.png
autowzry/assets/tpl1689666057241.png
autowzry/assets/tpl1689666083204.png
autowzry/assets/tpl1689666092009.png
autowzry/assets/tpl1689666117573.png
autowzry/assets/tpl1689666290543.png
autowzry/assets/tpl1689666324375.png
autowzry/assets/tpl1689666339749.png
autowzry/assets/tpl1689666367752.png
autowzry/assets/tpl1689666416575.png
autowzry/assets/tpl1689666921933.png
autowzry/assets/tpl1689667050980.png
autowzry/assets/tpl1689667226045.png
autowzry/assets/tpl1689667243845.png
autowzry/assets/tpl1689667256973.png
autowzry/assets/tpl1689667950453.png
autowzry/assets/tpl1689668119154.png
autowzry/assets/tpl1689668138416.png
autowzry/assets/tpl1690442560069.png
autowzry/assets/tpl1690442701046.png
autowzry/assets/tpl1690545494867.png
autowzry/assets/tpl1690545545580.png
autowzry/assets/tpl1690545762580.png
autowzry/assets/tpl1690545802859.png
autowzry/assets/tpl1690545854354.png
autowzry/assets/tpl1690545925867.png
autowzry/assets/tpl1690546610171.png
autowzry/assets/tpl1690546926096.png
autowzry/assets/tpl1690547053276.png
autowzry/assets/tpl1690547457483.png
autowzry/assets/tpl1690547491681.png
autowzry/assets/tpl1690552290188.png
autowzry/assets/tpl1691463676972.png
autowzry/assets/tpl1692946575591.png
autowzry/assets/tpl1692946702006.png
autowzry/assets/tpl1692946738054.png
autowzry/assets/tpl1692946837840.png
autowzry/assets/tpl1692946883784.png
autowzry/assets/tpl1692946938717.png
autowzry/assets/tpl1692947242096.png
autowzry/assets/tpl1692947351223.png
autowzry/assets/tpl1692949580380.png
autowzry/assets/tpl1692951324205.png
autowzry/assets/tpl1692951358456.png
autowzry/assets/tpl1692951432616.png
autowzry-2.4.1.4.dist-info/licenses/LICENSE
autowzry-2.4.1.4.dist-info/METADATA
autowzry-2.4.1.4.dist-info/WHEEL
autowzry-2.4.1.4.dist-info/entry_points.txt
autowzry-2.4.1.4.dist-info/top_level.txt
autowzry-2.4.1.4.dist-info/RECORD
