Metadata-Version: 2.4
Name: autowzry
Version: 2.4.1.4
Summary: 自动化农活演示
Author-email: cndaqiang <who@cndaqiang.ac.cn>
License: GPL-3.0-or-later
Project-URL: Homepage, https://github.com/cndaqiang/autowzry
Classifier: Development Status :: 5 - Production/Stable
Classifier: Intended Audience :: Developers
Classifier: License :: OSI Approved :: GNU General Public License v3 (GPLv3)
Classifier: Programming Language :: Python :: 3
Classifier: Programming Language :: Python :: 3.6
Classifier: Programming Language :: Python :: 3.7
Classifier: Programming Language :: Python :: 3.8
Classifier: Programming Language :: Python :: 3.9
Classifier: Programming Language :: Python :: 3.10
Classifier: Topic :: Software Development :: Libraries
Classifier: Topic :: Utilities
Requires-Python: >=3.6
License-File: LICENSE
Requires-Dist: airtest-mobileauto>=2.1.8.3
Dynamic: license-file
